README.md
setup.cfg
setup.py
blaugue/__init__.py
blaugue/api.py
blaugue/base.py
blaugue/bot.py
blaugue/chat.py
blaugue/post.py
blaugue/search.py
blaugue/tag.py
blaugue/user.py
blaugue.egg-info/PKG-INFO
blaugue.egg-info/SOURCES.txt
blaugue.egg-info/dependency_links.txt
blaugue.egg-info/requires.txt
blaugue.egg-info/top_level.txt