Metadata-Version: 2.1
Name: blaugue
Version: 0.0.3
Summary: Official Blaugue API package
Home-page: UNKNOWN
Author: CAMARM-DEV
Author-email: armand@camponovo.xyz
License: MIT
Keywords: conversion
Platform: UNKNOWN
Classifier: Development Status :: 5 - Production/Stable
Classifier: Intended Audience :: Developers
Classifier: License :: OSI Approved :: MIT License
Classifier: Programming Language :: Python :: 3
